LICENSE
MANIFEST.in
README.md
requirements-dev.txt
requirements.txt
setup.cfg
setup.py
cli-spinners/package.json
cli-spinners/spinners.json
spinners/__init__.py
spinners/constants.py
spinners/spinners.py
spinners.egg-info/PKG-INFO
spinners.egg-info/SOURCES.txt
spinners.egg-info/dependency_links.txt
spinners.egg-info/requires.txt
spinners.egg-info/top_level.txt