Metadata-Version: 1.0
Name: spinners
Version: 0.0.19
Summary: Spinners for terminals
Home-page: https://github.com/ManrajGrover/py-spinners
Author: Manraj Singh
Author-email: manrajsinghgrover@gmail.com
License: MIT
Keywords: cli,spinner,spinners,terminal,term,console,ascii,unicode,loading,indicator,progress,busy,wait,idle,json
Platform: UNKNOWN
